message_van/__init__.py
message_van/exceptions/__init__.py
message_van/exceptions/already_registered_handler_error.py
message_van/exceptions/unknown_handler_error.py
message_van/models/__init__.py
message_van/models/handler_signature.py
message_van/models/message_handler_type.py
message_van/models/message_handlers.py
message_van/models/message_van.py
message_van/models/message_van_meta.py
message_van/models/unit_of_work.py
message_van/models/base/__init__.py
message_van/models/base/command.py
message_van/models/base/command_handler.py
message_van/models/base/event.py
message_van/models/base/event_handler.py
message_van/models/base/message.py
message_van/models/base/message_handler.py
message_van/signature_lister/__init__.py
message_van/signature_lister/function_lister.py
message_van/signature_lister/module_importer.py
message_van/signature_lister/module_lister.py
message_van/signature_lister/signature_getter.py
message_van/signature_lister/signature_lister.py
message_van/util/__init__.py
message_van/util/package_dir.py
message_van-3.0.0.dist-info/METADATA
message_van-3.0.0.dist-info/WHEEL
message_van-3.0.0.dist-info/licenses/LICENSE.txt
message_van-3.0.0.dist-info/RECORD
