Metadata-Version: 2.4
Name: message-van
Version: 3.0.0
Summary: Python Event-Driven Architecture without the Administration.
Author-email: Thomas Vanhelden <thomas.vanhelden@gmail.com>
License: MIT
License-File: LICENSE.txt
Requires-Python: >=3.10
Requires-Dist: asyncclick>=8.0.0
Requires-Dist: pydantic>=1.10.0
Requires-Dist: tomli>=2.0.0
Requires-Dist: wrapt>=1.17.0
